[
    {
        "id": 81,
        "name": "ALVE létrák"
    },
    {
        "id": 72,
        "name": "Brennenstuhl hosszabbító kábelek és lámpatestek"
    },
    {
        "id": 78,
        "name": "Csapágyak, tömítések, ékszíjak és tartozékok"
    },
    {
        "id": 71,
        "name": "Egyéni védőeszközök Delta plus"
    },
    {
        "id": 69,
        "name": "Emelő- és kezelőtechnika YALE-PFAFF"
    },
    {
        "id": 66,
        "name": "Emelőtechnika, kampók és láncok 80-as és 100-as osztály"
    },
    {
        "id": 75,
        "name": "Építőkémia"
    },
    {
        "id": 68,
        "name": "Feszítőpántok – gurtnik és tartozékok"
    },
    {
        "id": 77,
        "name": "Háztartás és drogéria"
    },
    {
        "id": 65,
        "name": "Kötelek, láncok és gyorskötözők"
    },
    {
        "id": 64,
        "name": "Kötéltartozékok és rozsdamentes acél program"
    },
    {
        "id": 74,
        "name": "Kötő- és rögzítőelemek"
    },
    {
        "id": 67,
        "name": "Lánc- és textilhevederek"
    },
    {
        "id": 82,
        "name": "Mágnesek"
    },
    {
        "id": 70,
        "name": "Sarkak, szögvasak és vasalatok"
    },
    {
        "id": 76,
        "name": "Szerszámok"
    },
    {
        "id": 79,
        "name": "Szövetek"
    },
    {
        "id": 15,
        "name": "Uncategorized"
    },
    {
        "id": 73,
        "name": "Villanyszerelési anyagok"
    }
]