{
    "fetch_time": "2024-10-17T18:09:09.859910Z",
    "products": [
        {
            "name": "EXTOL   Brity do univerzálneho olamovacieho noža 18mm",
            "slug": "brity-do-univerzalneho-olamovacieho-noza-18mm_12550",
            "category_id": 411,
            "category_name": "Naradie Olamovacie Noze",
            "category_slug": "naradie-olamovacie-noze"
        },
        {
            "name": "EXTOL   Nôž olamovací kovový 18mm",
            "slug": "noz-olamovaci-kovovy-18mm-celokovovy_18852",
            "category_id": 411,
            "category_name": "Naradie Olamovacie Noze",
            "category_slug": "naradie-olamovacie-noze"
        },
        {
            "name": "FORTUM   Brity do olamovacieho noža - čierne 18mm",
            "slug": "brity-do-olamovacieho-noza-cierne-18mm_12549",
            "category_id": 411,
            "category_name": "Naradie Olamovacie Noze",
            "category_slug": "naradie-olamovacie-noze"
        },
        {
            "name": "EXTOL   Nôž olamovací kov / plast 18mm",
            "slug": "noz-olamovaci-kov-plast-18mm_12544",
            "category_id": 411,
            "category_name": "Naradie Olamovacie Noze",
            "category_slug": "naradie-olamovacie-noze"
        },
        {
            "name": "EXTOL   Nôž olamovací kov / guma 18mm",
            "slug": "noz-olamovaci-kovovy-18mm_12545",
            "category_id": 411,
            "category_name": "Naradie Olamovacie Noze",
            "category_slug": "naradie-olamovacie-noze"
        },
        {
            "name": "FORTUM   Nôž olamovací kovový - zatvárací 9mm",
            "slug": "noz-olamovaci-kovovy-zatvaraci-9mm_12547",
            "category_id": 411,
            "category_name": "Naradie Olamovacie Noze",
            "category_slug": "naradie-olamovacie-noze"
        },
        {
            "name": "OLFA   Brity do olamovacieho noža čierne 18mm",
            "slug": "brity-do-olamovacieho-noza-cierne-lbb-10b_13563",
            "category_id": 411,
            "category_name": "Naradie Olamovacie Noze",
            "category_slug": "naradie-olamovacie-noze"
        },
        {
            "name": "EXTOL   Nôž olamovací kovový 9mm",
            "slug": "noz-olamovaci-kovovy-9mm_12546",
            "category_id": 411,
            "category_name": "Naradie Olamovacie Noze",
            "category_slug": "naradie-olamovacie-noze"
        },
        {
            "name": "OLFA   Nôž univerzálny olamovací s pílkou 12,5mm",
            "slug": "noz-univerzalny-olamovaci-s-pilkou_13548",
            "category_id": 411,
            "category_name": "Naradie Olamovacie Noze",
            "category_slug": "naradie-olamovacie-noze"
        },
        {
            "name": "OLFA   Nôž univerzálny olamovací 9mm",
            "slug": "noz-univerzalny-olamovaci-silver_13553",
            "category_id": 411,
            "category_name": "Naradie Olamovacie Noze",
            "category_slug": "naradie-olamovacie-noze"
        },
        {
            "name": "OLFA   Nôž univerzálny olamovací 9mm",
            "slug": "noz-univerzalny-olamovaci-9mm_13554",
            "category_id": 411,
            "category_name": "Naradie Olamovacie Noze",
            "category_slug": "naradie-olamovacie-noze"
        },
        {
            "name": "OLFA   Nôž univerzálny olamovací 9mm",
            "slug": "noz-univerzalny-olamovaci-180_13555",
            "category_id": 411,
            "category_name": "Naradie Olamovacie Noze",
            "category_slug": "naradie-olamovacie-noze"
        },
        {
            "name": "OLFA   Nôž univerzálny olamovací 12,5mm",
            "slug": "noz-univerzalny-olamovaci-mt-1_13556",
            "category_id": 411,
            "category_name": "Naradie Olamovacie Noze",
            "category_slug": "naradie-olamovacie-noze"
        },
        {
            "name": "OLFA   Brity do škrabky čierne 18mm",
            "slug": "brity-do-skrabky-cierne-bs-10b_13560",
            "category_id": 411,
            "category_name": "Naradie Olamovacie Noze",
            "category_slug": "naradie-olamovacie-noze"
        },
        {
            "name": "OLFA   Brity do škrabky 18mm",
            "slug": "brity-do-skrabky-gsb-1s_13561",
            "category_id": 411,
            "category_name": "Naradie Olamovacie Noze",
            "category_slug": "naradie-olamovacie-noze"
        },
        {
            "name": "OLFA   Brity do olamovacieho noža čierne 25mm",
            "slug": "brity-do-olamovacieho-noza-cierne-hhb-5b_13562",
            "category_id": 411,
            "category_name": "Naradie Olamovacie Noze",
            "category_slug": "naradie-olamovacie-noze"
        },
        {
            "name": "OLFA   Brity do olamovacieho noža 12,5mm",
            "slug": "brity-do-olamovacieho-noza-mtm-10b_13565",
            "category_id": 411,
            "category_name": "Naradie Olamovacie Noze",
            "category_slug": "naradie-olamovacie-noze"
        },
        {
            "name": "OLFA   Pílový list 8mm",
            "slug": "pilovy-list-swb51b_13566",
            "category_id": 411,
            "category_name": "Naradie Olamovacie Noze",
            "category_slug": "naradie-olamovacie-noze"
        },
        {
            "name": "OLFA   Škrabka 18mm",
            "slug": "skrabka-xsr-300_13568",
            "category_id": 411,
            "category_name": "Naradie Olamovacie Noze",
            "category_slug": "naradie-olamovacie-noze"
        },
        {
            "name": "OLFA   Škrabka 18mm",
            "slug": "skrabka-gsr-13b_13567",
            "category_id": 411,
            "category_name": "Naradie Olamovacie Noze",
            "category_slug": "naradie-olamovacie-noze"
        },
        {
            "name": "EXTOL   Nôž univerzálny olamovací 18mm",
            "slug": "noz-univerzalny-olamovaci_11528",
            "category_id": 411,
            "category_name": "Naradie Olamovacie Noze",
            "category_slug": "naradie-olamovacie-noze"
        },
        {
            "name": "OLFA   Nôž univerzálny olamovací 18mm",
            "slug": "noz-univerzalny-olamovaci-olfa_13549",
            "category_id": 411,
            "category_name": "Naradie Olamovacie Noze",
            "category_slug": "naradie-olamovacie-noze"
        },
        {
            "name": "EXTOL   Brity do olamovacieho noža 18mm",
            "slug": "brity-do-olamovacieho-noza-18mm_12548",
            "category_id": 411,
            "category_name": "Naradie Olamovacie Noze",
            "category_slug": "naradie-olamovacie-noze"
        },
        {
            "name": "OLFA   Nôž univerzálny olamovací 9mm",
            "slug": "noz-univerzalny-olamovaci-xa-1_13557",
            "category_id": 411,
            "category_name": "Naradie Olamovacie Noze",
            "category_slug": "naradie-olamovacie-noze"
        },
        {
            "name": "OLFA   Nôž univerzálny olamovací 18mm",
            "slug": "noz-univerzalny-olamovaci-l5-al_13558",
            "category_id": 411,
            "category_name": "Naradie Olamovacie Noze",
            "category_slug": "naradie-olamovacie-noze"
        },
        {
            "name": "EXTOL   Brity do univerzálneho olamovacieho noža 9mm",
            "slug": "brity-do-univerzalneho-olamovacieho-noza-9mm_12551",
            "category_id": 411,
            "category_name": "Naradie Olamovacie Noze",
            "category_slug": "naradie-olamovacie-noze"
        }
    ]
}