{
    "fetch_time": "2024-10-17T18:19:08.675547Z",
    "products": [
        {
            "name": "Brennenstuhl   Cestovný adaptér GB 6,5x5cm",
            "slug": "cestovny-adapter-gb-adapter_798",
            "category_id": 420,
            "category_name": "Predlzovacie Kable A Svietidla Brennenstuhl Cestovne Adaptery",
            "category_slug": "predlzovacie-kable-a-svietidla-brennenstuhl-cestovne-adaptery"
        },
        {
            "name": "Brennenstuhl   Cestovná zástrčka DE + Vidlica Čína/Austrália",
            "slug": "cestovna-zastrcka-de-vidlica-cinaaustralia-adapter_1367",
            "category_id": 420,
            "category_name": "Predlzovacie Kable A Svietidla Brennenstuhl Cestovne Adaptery",
            "category_slug": "predlzovacie-kable-a-svietidla-brennenstuhl-cestovne-adaptery"
        },
        {
            "name": "Brennenstuhl   Cestovná zástrčka  DE + Vidlica Taliansko",
            "slug": "cestovna-zastrcka-de-vidlica-taliansko-adapter_1371",
            "category_id": 420,
            "category_name": "Predlzovacie Kable A Svietidla Brennenstuhl Cestovne Adaptery",
            "category_slug": "predlzovacie-kable-a-svietidla-brennenstuhl-cestovne-adaptery"
        },
        {
            "name": "Brennenstuhl   Cestovná zástrčka  DE + Vidlica Južná Afrika",
            "slug": "cestovna-zastrcka-de-vidlica-juzna-afrika-adapter_1368",
            "category_id": 420,
            "category_name": "Predlzovacie Kable A Svietidla Brennenstuhl Cestovne Adaptery",
            "category_slug": "predlzovacie-kable-a-svietidla-brennenstuhl-cestovne-adaptery"
        },
        {
            "name": "Brennenstuhl   Cestovný adaptér Austrália, Čína 7x5cm",
            "slug": "cestovny-adapter-australia-cina-adapter_802",
            "category_id": 420,
            "category_name": "Predlzovacie Kable A Svietidla Brennenstuhl Cestovne Adaptery",
            "category_slug": "predlzovacie-kable-a-svietidla-brennenstuhl-cestovne-adaptery"
        },
        {
            "name": "Brennenstuhl   Cestovná zástrčka  DE + Vidlica USA-Japonsko",
            "slug": "cestovna-zastrcka-de-vidlica-usa-japonsko-adapter_1375",
            "category_id": 420,
            "category_name": "Predlzovacie Kable A Svietidla Brennenstuhl Cestovne Adaptery",
            "category_slug": "predlzovacie-kable-a-svietidla-brennenstuhl-cestovne-adaptery"
        },
        {
            "name": "Brennenstuhl   Cestovný adaptér / zástrčkový adaptér EÚ na Veľkú Britániu 7x5cm",
            "slug": "cestovny-adapter-zastrckovy-adapter-eu-na-velku-britaniu-adapter_1364",
            "category_id": 420,
            "category_name": "Predlzovacie Kable A Svietidla Brennenstuhl Cestovne Adaptery",
            "category_slug": "predlzovacie-kable-a-svietidla-brennenstuhl-cestovne-adaptery"
        },
        {
            "name": "Brennenstuhl   Cestovný adaptér USA, Japonsko 6,5x4,8cm",
            "slug": "cestovny-adapter-usa-japonsko-adapter_804",
            "category_id": 420,
            "category_name": "Predlzovacie Kable A Svietidla Brennenstuhl Cestovne Adaptery",
            "category_slug": "predlzovacie-kable-a-svietidla-brennenstuhl-cestovne-adaptery"
        },
        {
            "name": "Brennenstuhl   Svetová cestovná zástrčka 7-Adaptérov 10A",
            "slug": "svetova-cestovna-zastrcka-7-adapterov-adapter_1362",
            "category_id": 420,
            "category_name": "Predlzovacie Kable A Svietidla Brennenstuhl Cestovne Adaptery",
            "category_slug": "predlzovacie-kable-a-svietidla-brennenstuhl-cestovne-adaptery"
        },
        {
            "name": "Brennenstuhl   Cestovný adaptér USA/Euro 5x5cm",
            "slug": "cestovny-adapter-usaeuro-adapter_1379",
            "category_id": 420,
            "category_name": "Predlzovacie Kable A Svietidla Brennenstuhl Cestovne Adaptery",
            "category_slug": "predlzovacie-kable-a-svietidla-brennenstuhl-cestovne-adaptery"
        }
    ]
}